{
  "project_info": {
    "project_number": "966539970399",
    "project_id": "vozmefit",
    "storage_bucket": "vozmefit.firebasestorage.app"
  },
  "client": [
    {
      "client_info": {
        "mobilesdk_app_id": "1:966539970399:android:d3c4e6b7eac9820f6b98ea",
        "android_client_info": {
          "package_name": "com.celia.vozmefit"
        }
      },
      "oauth_client": [],
      "api_key": [
        {
          "current_key": "AIzaSyA-8JFahnbHf7V1K1ul_X4OReVWR6h6fmI"
        }
      ],
      "services": {
        "appinvite_service": {
          "other_platform_oauth_client": []
        }
      }
    },
    {
      "client_info": {
        "mobilesdk_app_id": "1:966539970399:android:68f39f31a8c9f8fe6b98ea",
        "android_client_info": {
          "package_name": "com.example.vozmefit"
        }
      },
      "oauth_client": [],
      "api_key": [
        {
          "current_key": "AIzaSyA-8JFahnbHf7V1K1ul_X4OReVWR6h6fmI"
        }
      ],
      "services": {
        "appinvite_service": {
          "other_platform_oauth_client": []
        }
      }
    }
  ],
  "configuration_version": "1"
}